{
  "legislative_session": "2025-2026",
  "identifier": "HR 4658",
  "title": "Concerning Washington-Denmark relations.",
  "from_organization": "~{\"classification\": \"lower\"}",
  "classification": [
    "resolution"
  ],
  "subject": [],
  "abstracts": [],
  "other_titles": [],
  "other_identifiers": [],
  "actions": [
    {
      "description": "Introduced.",
      "date": "2025-04-08",
      "organization_id": "~{\"classification\": \"lower\"}",
      "classification": [
        "introduction"
      ],
      "related_entities": [],
      "_processing": {
        "log_file_created": "2025-10-25T03:55:00Z"
      }
    },
    {
      "description": "Adopted.",
      "date": "2025-04-08",
      "organization_id": "~{\"classification\": \"lower\"}",
      "classification": [
        "passage"
      ],
      "related_entities": [],
      "_processing": {
        "log_file_created": "2025-10-25T03:55:00Z"
      }
    }
  ],
  "sponsorships": [
    {
      "name": "Duerr",
      "classification": "primary",
      "entity_type": "person",
      "primary": true,
      "person_id": "~{\"name\": \"Duerr\"}",
      "organization_id": null
    },
    {
      "name": "Fitzgibbon",
      "classification": "cosponsor",
      "entity_type": "person",
      "primary": false,
      "person_id": "~{\"name\": \"Fitzgibbon\"}",
      "organization_id": null
    },
    {
      "name": "Zahn",
      "classification": "cosponsor",
      "entity_type": "person",
      "primary": false,
      "person_id": "~{\"name\": \"Zahn\"}",
      "organization_id": null
    },
    {
      "name": "Ramel",
      "classification": "cosponsor",
      "entity_type": "person",
      "primary": false,
      "person_id": "~{\"name\": \"Ramel\"}",
      "organization_id": null
    },
    {
      "name": "Chase",
      "classification": "cosponsor",
      "entity_type": "person",
      "primary": false,
      "person_id": "~{\"name\": \"Chase\"}",
      "organization_id": null
    },
    {
      "name": "Berry",
      "classification": "cosponsor",
      "entity_type": "person",
      "primary": false,
      "person_id": "~{\"name\": \"Berry\"}",
      "organization_id": null
    },
    {
      "name": "Parshley",
      "classification": "cosponsor",
      "entity_type": "person",
      "primary": false,
      "person_id": "~{\"name\": \"Parshley\"}",
      "organization_id": null
    },
    {
      "name": "Taylor",
      "classification": "cosponsor",
      "entity_type": "person",
      "primary": false,
      "person_id": "~{\"name\": \"Taylor\"}",
      "organization_id": null
    },
    {
      "name": "Abell",
      "classification": "cosponsor",
      "entity_type": "person",
      "primary": false,
      "person_id": "~{\"name\": \"Abell\"}",
      "organization_id": null
    },
    {
      "name": "Walen",
      "classification": "cosponsor",
      "entity_type": "person",
      "primary": false,
      "person_id": "~{\"name\": \"Walen\"}",
      "organization_id": null
    },
    {
      "name": "Doglio",
      "classification": "cosponsor",
      "entity_type": "person",
      "primary": false,
      "person_id": "~{\"name\": \"Doglio\"}",
      "organization_id": null
    },
    {
      "name": "Bronoske",
      "classification": "cosponsor",
      "entity_type": "person",
      "primary": false,
      "person_id": "~{\"name\": \"Bronoske\"}",
      "organization_id": null
    },
    {
      "name": "Fosse",
      "classification": "cosponsor",
      "entity_type": "person",
      "primary": false,
      "person_id": "~{\"name\": \"Fosse\"}",
      "organization_id": null
    },
    {
      "name": "Scott",
      "classification": "cosponsor",
      "entity_type": "person",
      "primary": false,
      "person_id": "~{\"name\": \"Scott\"}",
      "organization_id": null
    },
    {
      "name": "Ryu",
      "classification": "cosponsor",
      "entity_type": "person",
      "primary": false,
      "person_id": "~{\"name\": \"Ryu\"}",
      "organization_id": null
    },
    {
      "name": "Timmons",
      "classification": "cosponsor",
      "entity_type": "person",
      "primary": false,
      "person_id": "~{\"name\": \"Timmons\"}",
      "organization_id": null
    },
    {
      "name": "Stonier",
      "classification": "cosponsor",
      "entity_type": "person",
      "primary": false,
      "person_id": "~{\"name\": \"Stonier\"}",
      "organization_id": null
    },
    {
      "name": "Leavitt",
      "classification": "cosponsor",
      "entity_type": "person",
      "primary": false,
      "person_id": "~{\"name\": \"Leavitt\"}",
      "organization_id": null
    },
    {
      "name": "Berg",
      "classification": "cosponsor",
      "entity_type": "person",
      "primary": false,
      "person_id": "~{\"name\": \"Berg\"}",
      "organization_id": null
    }
  ],
  "related_bills": [],
  "versions": [
    {
      "note": "Resolution",
      "links": [
        {
          "url": "http://lawfilesext.leg.wa.gov/Biennium/2025-26/Htm/Bills/House%20Resolutions/4658-.htm",
          "media_type": "text/html"
        },
        {
          "url": "http://lawfilesext.leg.wa.gov/Biennium/2025-26/Pdf/Bills/House%20Resolutions/4658-.pdf",
          "media_type": "application/pdf"
        },
        {
          "url": "http://lawfilesext.leg.wa.gov/Biennium/2025-26/Htm/Bills/House%20Resolutions/4658-Washington-Denmark%20relations.htm",
          "media_type": "text/html"
        },
        {
          "url": "http://lawfilesext.leg.wa.gov/Biennium/2025-26/Pdf/Bills/House%20Resolutions/4658-Washington-Denmark%20relations.pdf",
          "media_type": "application/pdf"
        }
      ],
      "date": "",
      "classification": ""
    }
  ],
  "documents": [],
  "citations": [],
  "sources": [
    {
      "url": "https://app.leg.wa.gov/billsummary/?BillNumber=4658&Year=2025&Initiative=false",
      "note": ""
    }
  ],
  "extras": {},
  "jurisdiction": {
    "id": "ocd-jurisdiction/country:us/state:wa/government",
    "name": "Washington",
    "classification": "state",
    "division_id": "ocd-division/country:us/state:wa"
  },
  "_processing": {
    "logs_latest_update": "2025-10-25T03:55:00Z",
    "text_extraction_latest_update": "2025-10-26T10:02:29.848523Z"
  }
}