{
  "legislative_session": "2025-2026",
  "identifier": "HB 1300",
  "title": "Transferring dedicated accounts for certain professional licenses to the business and professions account.",
  "from_organization": "~{\"classification\": \"lower\"}",
  "classification": [
    "bill"
  ],
  "subject": [],
  "abstracts": [],
  "other_titles": [],
  "other_identifiers": [],
  "actions": [
    {
      "description": "First reading, referred to Appropriations.",
      "date": "2025-01-15",
      "organization_id": "~{\"classification\": \"lower\"}",
      "classification": [
        "reading-1"
      ],
      "related_entities": [],
      "_processing": {
        "log_file_created": "2025-10-25T03:55:00Z"
      }
    },
    {
      "description": "Public hearing in the House Committee on Appropriations at 4:00 PM.",
      "date": "2025-01-23",
      "organization_id": "~{\"classification\": \"lower\"}",
      "classification": [],
      "related_entities": [],
      "_processing": {
        "log_file_created": "2025-10-25T03:55:00Z"
      }
    },
    {
      "description": "Executive action taken in the House Committee on Appropriations at 4:00 PM.",
      "date": "2025-01-27",
      "organization_id": "~{\"classification\": \"lower\"}",
      "classification": [],
      "related_entities": [],
      "_processing": {
        "log_file_created": "2025-10-25T03:55:00Z"
      }
    },
    {
      "description": "APP - Majority; do pass.",
      "date": "2025-01-27",
      "organization_id": "~{\"classification\": \"lower\"}",
      "classification": [
        "committee-passage-favorable"
      ],
      "related_entities": [],
      "_processing": {
        "log_file_created": "2025-10-25T03:55:00Z"
      }
    },
    {
      "description": "Referred to Rules 2 Review.",
      "date": "2025-01-29",
      "organization_id": "~{\"classification\": \"lower\"}",
      "classification": [
        "referral-committee"
      ],
      "related_entities": [],
      "_processing": {
        "log_file_created": "2025-10-25T03:55:00Z"
      }
    },
    {
      "description": "Rules Committee relieved of further consideration.  Placed on second reading.",
      "date": "2025-02-05",
      "organization_id": "~{\"classification\": \"lower\"}",
      "classification": [
        "reading-2"
      ],
      "related_entities": [],
      "_processing": {
        "log_file_created": "2025-10-25T03:55:00Z"
      }
    },
    {
      "description": "Rules suspended.  Placed on Third Reading.",
      "date": "2025-02-06",
      "organization_id": "~{\"classification\": \"lower\"}",
      "classification": [
        "reading-3"
      ],
      "related_entities": [],
      "_processing": {
        "log_file_created": "2025-10-25T03:55:00Z"
      }
    },
    {
      "description": "Third reading, passed; yeas, 96; nays, 0; absent, 0; excused, 2.",
      "date": "2025-02-06",
      "organization_id": "~{\"classification\": \"lower\"}",
      "classification": [
        "reading-3"
      ],
      "related_entities": [],
      "_processing": {
        "log_file_created": "2025-10-25T03:55:00Z"
      }
    },
    {
      "description": "First reading, referred to Business, Financial Services & Trade.",
      "date": "2025-02-07",
      "organization_id": "~{\"classification\": \"upper\"}",
      "classification": [
        "reading-1"
      ],
      "related_entities": [],
      "_processing": {
        "log_file_created": "2025-10-25T03:55:00Z"
      }
    },
    {
      "description": "Public hearing in the Senate Committee on Business, Financial Services & Trade at 8:00 AM.",
      "date": "2025-03-13",
      "organization_id": "~{\"classification\": \"upper\"}",
      "classification": [],
      "related_entities": [],
      "_processing": {
        "log_file_created": "2025-10-25T03:55:00Z"
      }
    },
    {
      "description": "By resolution, returned to House Rules Committee for third reading.",
      "date": "2025-04-27",
      "organization_id": "~{\"classification\": \"upper\"}",
      "classification": [],
      "related_entities": [],
      "_processing": {
        "log_file_created": "2025-10-25T03:55:00Z"
      }
    }
  ],
  "sponsorships": [
    {
      "name": "Donaghy",
      "classification": "primary",
      "entity_type": "person",
      "primary": true,
      "person_id": "~{\"name\": \"Donaghy\"}",
      "organization_id": null
    },
    {
      "name": "Reeves",
      "classification": "cosponsor",
      "entity_type": "person",
      "primary": false,
      "person_id": "~{\"name\": \"Reeves\"}",
      "organization_id": null
    },
    {
      "name": "Ormsby",
      "classification": "cosponsor",
      "entity_type": "person",
      "primary": false,
      "person_id": "~{\"name\": \"Ormsby\"}",
      "organization_id": null
    }
  ],
  "related_bills": [],
  "versions": [
    {
      "note": "Bill",
      "links": [
        {
          "url": "http://lawfilesext.leg.wa.gov/Biennium/2025-26/Htm/Bills/House%20Bills/1300.htm",
          "media_type": "text/html"
        },
        {
          "url": "http://lawfilesext.leg.wa.gov/Biennium/2025-26/Pdf/Bills/House%20Bills/1300.pdf",
          "media_type": "application/pdf"
        }
      ],
      "date": "",
      "classification": ""
    }
  ],
  "documents": [
    {
      "note": "Report",
      "links": [
        {
          "url": "http://lawfilesext.leg.wa.gov/Biennium/2025-26/Htm/Bill%20Reports/House/1300%20HBA%20APP%2025.htm",
          "media_type": "text/html"
        },
        {
          "url": "http://lawfilesext.leg.wa.gov/Biennium/2025-26/Htm/Bill%20Reports/House/1300%20HBR%20APH%2025.htm",
          "media_type": "text/html"
        },
        {
          "url": "http://lawfilesext.leg.wa.gov/Biennium/2025-26/Htm/Bill%20Reports/House/1300%20HBR%20APP%2025.htm",
          "media_type": "text/html"
        }
      ],
      "date": "",
      "classification": ""
    }
  ],
  "citations": [
    {
      "publication": "Revised Code of Washington",
      "citation": "18.08.240",
      "citation_type": "proposed",
      "effective": null,
      "expires": null,
      "url": "https://app.leg.wa.gov/RCW/default.aspx?cite=18.08.240"
    },
    {
      "publication": "Revised Code of Washington",
      "citation": "18.140.260",
      "citation_type": "proposed",
      "effective": null,
      "expires": null,
      "url": "https://app.leg.wa.gov/RCW/default.aspx?cite=18.140.260"
    },
    {
      "publication": "Revised Code of Washington",
      "citation": "18.220.120",
      "citation_type": "proposed",
      "effective": null,
      "expires": null,
      "url": "https://app.leg.wa.gov/RCW/default.aspx?cite=18.220.120"
    },
    {
      "publication": "Revised Code of Washington",
      "citation": "18.310.160",
      "citation_type": "proposed",
      "effective": null,
      "expires": null,
      "url": "https://app.leg.wa.gov/RCW/default.aspx?cite=18.310.160"
    },
    {
      "publication": "Revised Code of Washington",
      "citation": "18.39.810",
      "citation_type": "proposed",
      "effective": null,
      "expires": null,
      "url": "https://app.leg.wa.gov/RCW/default.aspx?cite=18.39.810"
    },
    {
      "publication": "Revised Code of Washington",
      "citation": "18.96.210",
      "citation_type": "proposed",
      "effective": null,
      "expires": null,
      "url": "https://app.leg.wa.gov/RCW/default.aspx?cite=18.96.210"
    },
    {
      "publication": "Revised Code of Washington",
      "citation": "43.24.150",
      "citation_type": "proposed",
      "effective": null,
      "expires": null,
      "url": "https://app.leg.wa.gov/RCW/default.aspx?cite=43.24.150"
    }
  ],
  "sources": [
    {
      "url": "https://app.leg.wa.gov/billsummary/?BillNumber=1300&Year=2025&Initiative=false",
      "note": ""
    }
  ],
  "extras": {},
  "jurisdiction": {
    "id": "ocd-jurisdiction/country:us/state:wa/government",
    "name": "Washington",
    "classification": "state",
    "division_id": "ocd-division/country:us/state:wa"
  },
  "_processing": {
    "logs_latest_update": "2025-10-25T03:55:00Z",
    "text_extraction_latest_update": "2025-10-30T09:06:18.944435Z"
  }
}