{
  "legislative_session": "2025-2026",
  "identifier": "SB 5415",
  "title": "Concerning financial feasibility of collective bargaining agreements.",
  "from_organization": "~{\"classification\": \"upper\"}",
  "classification": [
    "bill"
  ],
  "subject": [],
  "abstracts": [],
  "other_titles": [],
  "other_identifiers": [],
  "actions": [
    {
      "description": "First reading, referred to Ways & Means.",
      "date": "2025-01-22",
      "organization_id": "~{\"classification\": \"upper\"}",
      "classification": [
        "reading-1"
      ],
      "related_entities": [],
      "_processing": {
        "log_file_created": "2025-10-25T03:55:02Z"
      }
    }
  ],
  "sponsorships": [
    {
      "name": "Gildon",
      "classification": "primary",
      "entity_type": "person",
      "primary": true,
      "person_id": "~{\"name\": \"Gildon\"}",
      "organization_id": null
    }
  ],
  "related_bills": [],
  "versions": [
    {
      "note": "Bill",
      "links": [
        {
          "url": "http://lawfilesext.leg.wa.gov/Biennium/2025-26/Htm/Bills/Senate%20Bills/5415.htm",
          "media_type": "text/html"
        },
        {
          "url": "http://lawfilesext.leg.wa.gov/Biennium/2025-26/Pdf/Bills/Senate%20Bills/5415.pdf",
          "media_type": "application/pdf"
        }
      ],
      "date": "",
      "classification": ""
    }
  ],
  "documents": [],
  "citations": [
    {
      "publication": "Revised Code of Washington",
      "citation": "41.56.028",
      "citation_type": "proposed",
      "effective": null,
      "expires": null,
      "url": "https://app.leg.wa.gov/RCW/default.aspx?cite=41.56.028"
    },
    {
      "publication": "Revised Code of Washington",
      "citation": "41.56.029",
      "citation_type": "proposed",
      "effective": null,
      "expires": null,
      "url": "https://app.leg.wa.gov/RCW/default.aspx?cite=41.56.029"
    },
    {
      "publication": "Revised Code of Washington",
      "citation": "41.56.473",
      "citation_type": "proposed",
      "effective": null,
      "expires": null,
      "url": "https://app.leg.wa.gov/RCW/default.aspx?cite=41.56.473"
    },
    {
      "publication": "Revised Code of Washington",
      "citation": "41.56.500",
      "citation_type": "proposed",
      "effective": null,
      "expires": null,
      "url": "https://app.leg.wa.gov/RCW/default.aspx?cite=41.56.500"
    },
    {
      "publication": "Revised Code of Washington",
      "citation": "41.56.510",
      "citation_type": "proposed",
      "effective": null,
      "expires": null,
      "url": "https://app.leg.wa.gov/RCW/default.aspx?cite=41.56.510"
    },
    {
      "publication": "Revised Code of Washington",
      "citation": "41.56.515",
      "citation_type": "proposed",
      "effective": null,
      "expires": null,
      "url": "https://app.leg.wa.gov/RCW/default.aspx?cite=41.56.515"
    },
    {
      "publication": "Revised Code of Washington",
      "citation": "41.59.105",
      "citation_type": "proposed",
      "effective": null,
      "expires": null,
      "url": "https://app.leg.wa.gov/RCW/default.aspx?cite=41.59.105"
    },
    {
      "publication": "Revised Code of Washington",
      "citation": "41.80.010",
      "citation_type": "proposed",
      "effective": null,
      "expires": null,
      "url": "https://app.leg.wa.gov/RCW/default.aspx?cite=41.80.010"
    },
    {
      "publication": "Revised Code of Washington",
      "citation": "47.64.170",
      "citation_type": "proposed",
      "effective": null,
      "expires": null,
      "url": "https://app.leg.wa.gov/RCW/default.aspx?cite=47.64.170"
    },
    {
      "publication": "Revised Code of Washington",
      "citation": "74.39a.300",
      "citation_type": "proposed",
      "effective": null,
      "expires": null,
      "url": "https://app.leg.wa.gov/RCW/default.aspx?cite=74.39a.300"
    },
    {
      "publication": "Revised Code of Washington",
      "citation": "74.39a.530",
      "citation_type": "proposed",
      "effective": null,
      "expires": null,
      "url": "https://app.leg.wa.gov/RCW/default.aspx?cite=74.39a.530"
    }
  ],
  "sources": [
    {
      "url": "https://app.leg.wa.gov/billsummary/?BillNumber=5415&Year=2025&Initiative=false",
      "note": ""
    }
  ],
  "extras": {},
  "jurisdiction": {
    "id": "ocd-jurisdiction/country:us/state:wa/government",
    "name": "Washington",
    "classification": "state",
    "division_id": "ocd-division/country:us/state:wa"
  },
  "_processing": {
    "logs_latest_update": "2025-10-25T03:55:02Z",
    "text_extraction_latest_update": "2025-10-30T09:41:50.196432Z"
  }
}