{
  "legislative_session": "2025-2026",
  "identifier": "HB 1478",
  "title": "Modifying the manner of death listed in a death certificate following a conviction of controlled substance homicide.",
  "from_organization": "~{\"classification\": \"lower\"}",
  "classification": [
    "bill"
  ],
  "subject": [],
  "abstracts": [],
  "other_titles": [],
  "other_identifiers": [],
  "actions": [
    {
      "description": "First reading, referred to Health Care & Wellness.",
      "date": "2025-01-21",
      "organization_id": "~{\"classification\": \"lower\"}",
      "classification": [
        "reading-1"
      ],
      "related_entities": [],
      "_processing": {
        "log_file_created": "2025-10-25T03:55:02Z"
      }
    }
  ],
  "sponsorships": [
    {
      "name": "Lekanoff",
      "classification": "primary",
      "entity_type": "person",
      "primary": true,
      "person_id": "~{\"name\": \"Lekanoff\"}",
      "organization_id": null
    },
    {
      "name": "Reed",
      "classification": "cosponsor",
      "entity_type": "person",
      "primary": false,
      "person_id": "~{\"name\": \"Reed\"}",
      "organization_id": null
    }
  ],
  "related_bills": [],
  "versions": [
    {
      "note": "Bill",
      "links": [
        {
          "url": "http://lawfilesext.leg.wa.gov/Biennium/2025-26/Htm/Bills/House%20Bills/1478.htm",
          "media_type": "text/html"
        },
        {
          "url": "http://lawfilesext.leg.wa.gov/Biennium/2025-26/Pdf/Bills/House%20Bills/1478.pdf",
          "media_type": "application/pdf"
        }
      ],
      "date": "",
      "classification": ""
    }
  ],
  "documents": [],
  "citations": [
    {
      "publication": "Revised Code of Washington",
      "citation": "2.32",
      "citation_type": "proposed",
      "effective": null,
      "expires": null,
      "url": "https://app.leg.wa.gov/RCW/default.aspx?cite=2.32"
    },
    {
      "publication": "Revised Code of Washington",
      "citation": "70.58a.200",
      "citation_type": "proposed",
      "effective": null,
      "expires": null,
      "url": "https://app.leg.wa.gov/RCW/default.aspx?cite=70.58a.200"
    }
  ],
  "sources": [
    {
      "url": "https://app.leg.wa.gov/billsummary/?BillNumber=1478&Year=2025&Initiative=false",
      "note": ""
    }
  ],
  "extras": {},
  "jurisdiction": {
    "id": "ocd-jurisdiction/country:us/state:wa/government",
    "name": "Washington",
    "classification": "state",
    "division_id": "ocd-division/country:us/state:wa"
  },
  "_processing": {
    "logs_latest_update": "2025-10-25T03:55:02Z",
    "text_extraction_latest_update": "2025-10-27T09:13:15.153484Z"
  }
}