{
  "legislative_session": "2025-2026",
  "identifier": "SB 5794",
  "title": "Adopting recommendations from the tax preference performance review process, eliminating obsolete tax preferences, clarifying legislative intent, and addressing changes in constitutional law.",
  "from_organization": "~{\"classification\": \"upper\"}",
  "classification": [
    "bill"
  ],
  "subject": [],
  "abstracts": [],
  "other_titles": [],
  "other_identifiers": [],
  "actions": [
    {
      "description": "First reading, referred to Ways & Means.",
      "date": "2025-03-21",
      "organization_id": "~{\"classification\": \"upper\"}",
      "classification": [
        "reading-1"
      ],
      "related_entities": [],
      "_processing": {
        "log_file_created": "2025-10-25T03:55:00Z"
      }
    },
    {
      "description": "Public hearing in the Senate Committee on Ways & Means at 4:00 PM.",
      "date": "2025-03-31",
      "organization_id": "~{\"classification\": \"upper\"}",
      "classification": [],
      "related_entities": [],
      "_processing": {
        "log_file_created": "2025-10-25T03:55:00Z"
      }
    },
    {
      "description": "Executive action taken in the Senate Committee on Ways & Means at 9:00 AM.",
      "date": "2025-04-18",
      "organization_id": "~{\"classification\": \"upper\"}",
      "classification": [],
      "related_entities": [],
      "_processing": {
        "log_file_created": "2025-10-25T03:55:00Z"
      }
    },
    {
      "description": "WM - Majority; 1st substitute bill be substituted, do pass.",
      "date": "2025-04-18",
      "organization_id": "~{\"classification\": \"upper\"}",
      "classification": [
        "substitution"
      ],
      "related_entities": [],
      "_processing": {
        "log_file_created": "2025-10-25T03:55:00Z"
      }
    },
    {
      "description": "Minority; do not pass.",
      "date": "2025-04-18",
      "organization_id": "~{\"classification\": \"upper\"}",
      "classification": [
        "committee-passage-unfavorable"
      ],
      "related_entities": [],
      "_processing": {
        "log_file_created": "2025-10-25T03:55:00Z"
      }
    },
    {
      "description": "Passed to Rules Committee for second reading.",
      "date": "2025-04-19",
      "organization_id": "~{\"classification\": \"upper\"}",
      "classification": [],
      "related_entities": [],
      "_processing": {
        "log_file_created": "2025-10-25T03:55:00Z"
      }
    },
    {
      "description": "Placed on second reading by Rules Committee.",
      "date": "2025-04-19",
      "organization_id": "~{\"classification\": \"upper\"}",
      "classification": [
        "reading-2"
      ],
      "related_entities": [],
      "_processing": {
        "log_file_created": "2025-10-25T03:55:00Z"
      }
    },
    {
      "description": "1st substitute bill substituted (WM 25).",
      "date": "2025-04-19",
      "organization_id": "~{\"classification\": \"upper\"}",
      "classification": [
        "substitution"
      ],
      "related_entities": [],
      "_processing": {
        "log_file_created": "2025-10-25T03:55:00Z"
      }
    },
    {
      "description": "Floor amendment(s) adopted.",
      "date": "2025-04-19",
      "organization_id": "~{\"classification\": \"upper\"}",
      "classification": [],
      "related_entities": [],
      "_processing": {
        "log_file_created": "2025-10-25T03:55:00Z"
      }
    },
    {
      "description": "Rules suspended.  Placed on Third Reading.",
      "date": "2025-04-19",
      "organization_id": "~{\"classification\": \"upper\"}",
      "classification": [
        "reading-3"
      ],
      "related_entities": [],
      "_processing": {
        "log_file_created": "2025-10-25T03:55:00Z"
      }
    },
    {
      "description": "Third reading, passed; yeas, 26; nays, 22; absent, 0; excused, 1.",
      "date": "2025-04-19",
      "organization_id": "~{\"classification\": \"upper\"}",
      "classification": [
        "reading-3"
      ],
      "related_entities": [],
      "_processing": {
        "log_file_created": "2025-10-25T03:55:00Z"
      }
    },
    {
      "description": "First reading, referred to Finance.",
      "date": "2025-04-21",
      "organization_id": "~{\"classification\": \"lower\"}",
      "classification": [
        "reading-1"
      ],
      "related_entities": [],
      "_processing": {
        "log_file_created": "2025-10-25T03:55:00Z"
      }
    },
    {
      "description": "Public hearing in the House Committee on Finance at 9:00 AM.",
      "date": "2025-04-21",
      "organization_id": "~{\"classification\": \"lower\"}",
      "classification": [],
      "related_entities": [],
      "_processing": {
        "log_file_created": "2025-10-25T03:55:00Z"
      }
    },
    {
      "description": "Executive action taken in the House Committee on Finance at 11:30 AM.",
      "date": "2025-04-22",
      "organization_id": "~{\"classification\": \"lower\"}",
      "classification": [],
      "related_entities": [],
      "_processing": {
        "log_file_created": "2025-10-25T03:55:00Z"
      }
    },
    {
      "description": "FIN - Majority; do pass with amendment(s).",
      "date": "2025-04-22",
      "organization_id": "~{\"classification\": \"lower\"}",
      "classification": [
        "committee-passage-favorable"
      ],
      "related_entities": [],
      "_processing": {
        "log_file_created": "2025-10-25T03:55:00Z"
      }
    },
    {
      "description": "Minority; do not pass.",
      "date": "2025-04-22",
      "organization_id": "~{\"classification\": \"lower\"}",
      "classification": [
        "committee-passage-unfavorable"
      ],
      "related_entities": [],
      "_processing": {
        "log_file_created": "2025-10-25T03:55:00Z"
      }
    },
    {
      "description": "Referred to Rules 2 Review.",
      "date": "2025-04-22",
      "organization_id": "~{\"classification\": \"lower\"}",
      "classification": [
        "referral-committee"
      ],
      "related_entities": [],
      "_processing": {
        "log_file_created": "2025-10-25T03:55:00Z"
      }
    },
    {
      "description": "Rules Committee relieved of further consideration.  Placed on second reading.",
      "date": "2025-04-23",
      "organization_id": "~{\"classification\": \"lower\"}",
      "classification": [
        "reading-2"
      ],
      "related_entities": [],
      "_processing": {
        "log_file_created": "2025-10-25T03:55:00Z"
      }
    },
    {
      "description": "Committee amendment(s) adopted as amended.",
      "date": "2025-04-23",
      "organization_id": "~{\"classification\": \"lower\"}",
      "classification": [],
      "related_entities": [],
      "_processing": {
        "log_file_created": "2025-10-25T03:55:00Z"
      }
    },
    {
      "description": "Rules suspended.  Placed on Third Reading.",
      "date": "2025-04-23",
      "organization_id": "~{\"classification\": \"lower\"}",
      "classification": [
        "reading-3"
      ],
      "related_entities": [],
      "_processing": {
        "log_file_created": "2025-10-25T03:55:00Z"
      }
    },
    {
      "description": "Third reading, passed; yeas, 53; nays, 45; absent, 0; excused, 0.",
      "date": "2025-04-23",
      "organization_id": "~{\"classification\": \"lower\"}",
      "classification": [
        "reading-3"
      ],
      "related_entities": [],
      "_processing": {
        "log_file_created": "2025-10-25T03:55:00Z"
      }
    },
    {
      "description": "Senate concurred in House amendments.",
      "date": "2025-04-24",
      "organization_id": "~{\"classification\": \"upper\"}",
      "classification": [],
      "related_entities": [],
      "_processing": {
        "log_file_created": "2025-10-25T03:55:00Z"
      }
    },
    {
      "description": "Passed final passage; yeas, 26; nays, 22; absent, 0; excused, 0.",
      "date": "2025-04-24",
      "organization_id": "~{\"classification\": \"upper\"}",
      "classification": [
        "passage"
      ],
      "related_entities": [],
      "_processing": {
        "log_file_created": "2025-10-25T03:55:00Z"
      }
    },
    {
      "description": "President signed.",
      "date": "2025-04-25",
      "organization_id": "~{\"classification\": \"upper\"}",
      "classification": [
        "passage"
      ],
      "related_entities": [],
      "_processing": {
        "log_file_created": "2025-10-25T03:55:00Z"
      }
    },
    {
      "description": "Speaker signed.",
      "date": "2025-04-26",
      "organization_id": "~{\"classification\": \"lower\"}",
      "classification": [
        "passage"
      ],
      "related_entities": [],
      "_processing": {
        "log_file_created": "2025-10-25T03:55:00Z"
      }
    },
    {
      "description": "Delivered to Governor.",
      "date": "2025-04-27",
      "organization_id": "~{\"classification\": \"executive\"}",
      "classification": [
        "executive-receipt"
      ],
      "related_entities": [],
      "_processing": {
        "log_file_created": "2025-10-25T03:55:00Z"
      }
    },
    {
      "description": "Governor partially vetoed.",
      "date": "2025-05-20",
      "organization_id": "~{\"classification\": \"executive\"}",
      "classification": [
        "executive-veto-line-item"
      ],
      "related_entities": [],
      "_processing": {
        "log_file_created": "2025-10-25T03:55:00Z"
      }
    },
    {
      "description": "Chapter 423, 2025 Laws PV.",
      "date": "2025-05-20",
      "organization_id": "~{\"classification\": \"executive\"}",
      "classification": [
        "became-law"
      ],
      "related_entities": [],
      "_processing": {
        "log_file_created": "2025-10-25T03:55:00Z"
      }
    },
    {
      "description": "Effective date 1/1/2026*.",
      "date": "2025-05-20",
      "organization_id": "~{\"classification\": \"executive\"}",
      "classification": [
        "became-law"
      ],
      "related_entities": [],
      "_processing": {
        "log_file_created": "2025-10-25T03:55:00Z"
      }
    }
  ],
  "sponsorships": [
    {
      "name": "Salomon",
      "classification": "primary",
      "entity_type": "person",
      "primary": true,
      "person_id": "~{\"name\": \"Salomon\"}",
      "organization_id": null
    },
    {
      "name": "Lovelett",
      "classification": "cosponsor",
      "entity_type": "person",
      "primary": false,
      "person_id": "~{\"name\": \"Lovelett\"}",
      "organization_id": null
    },
    {
      "name": "Alvarado",
      "classification": "cosponsor",
      "entity_type": "person",
      "primary": false,
      "person_id": "~{\"name\": \"Alvarado\"}",
      "organization_id": null
    },
    {
      "name": "Bateman",
      "classification": "cosponsor",
      "entity_type": "person",
      "primary": false,
      "person_id": "~{\"name\": \"Bateman\"}",
      "organization_id": null
    },
    {
      "name": "Dhingra",
      "classification": "cosponsor",
      "entity_type": "person",
      "primary": false,
      "person_id": "~{\"name\": \"Dhingra\"}",
      "organization_id": null
    },
    {
      "name": "Frame",
      "classification": "cosponsor",
      "entity_type": "person",
      "primary": false,
      "person_id": "~{\"name\": \"Frame\"}",
      "organization_id": null
    },
    {
      "name": "Hasegawa",
      "classification": "cosponsor",
      "entity_type": "person",
      "primary": false,
      "person_id": "~{\"name\": \"Hasegawa\"}",
      "organization_id": null
    },
    {
      "name": "Nobles",
      "classification": "cosponsor",
      "entity_type": "person",
      "primary": false,
      "person_id": "~{\"name\": \"Nobles\"}",
      "organization_id": null
    },
    {
      "name": "Ramos",
      "classification": "cosponsor",
      "entity_type": "person",
      "primary": false,
      "person_id": "~{\"name\": \"Ramos\"}",
      "organization_id": null
    },
    {
      "name": "Riccelli",
      "classification": "cosponsor",
      "entity_type": "person",
      "primary": false,
      "person_id": "~{\"name\": \"Riccelli\"}",
      "organization_id": null
    },
    {
      "name": "Trudeau",
      "classification": "cosponsor",
      "entity_type": "person",
      "primary": false,
      "person_id": "~{\"name\": \"Trudeau\"}",
      "organization_id": null
    },
    {
      "name": "Wellman",
      "classification": "cosponsor",
      "entity_type": "person",
      "primary": false,
      "person_id": "~{\"name\": \"Wellman\"}",
      "organization_id": null
    }
  ],
  "related_bills": [],
  "versions": [
    {
      "note": "Engrossed Substitute Bill",
      "links": [
        {
          "url": "http://lawfilesext.leg.wa.gov/Biennium/2025-26/Htm/Bills/Senate%20Bills/5794-S.E.htm",
          "media_type": "text/html"
        },
        {
          "url": "http://lawfilesext.leg.wa.gov/Biennium/2025-26/Pdf/Bills/Senate%20Bills/5794-S.E.pdf",
          "media_type": "application/pdf"
        }
      ],
      "date": "",
      "classification": ""
    },
    {
      "note": "Substitute Bill",
      "links": [
        {
          "url": "http://lawfilesext.leg.wa.gov/Biennium/2025-26/Htm/Bills/Senate%20Bills/5794-S.htm",
          "media_type": "text/html"
        },
        {
          "url": "http://lawfilesext.leg.wa.gov/Biennium/2025-26/Pdf/Bills/Senate%20Bills/5794-S.pdf",
          "media_type": "application/pdf"
        }
      ],
      "date": "",
      "classification": ""
    },
    {
      "note": "Bill",
      "links": [
        {
          "url": "http://lawfilesext.leg.wa.gov/Biennium/2025-26/Htm/Bills/Senate%20Bills/5794.htm",
          "media_type": "text/html"
        },
        {
          "url": "http://lawfilesext.leg.wa.gov/Biennium/2025-26/Pdf/Bills/Senate%20Bills/5794.pdf",
          "media_type": "application/pdf"
        }
      ],
      "date": "",
      "classification": ""
    },
    {
      "note": "Substitute Passed Legislature",
      "links": [
        {
          "url": "http://lawfilesext.leg.wa.gov/Biennium/2025-26/Htm/Bills/Senate%20Passed%20Legislature/5794-S.PL.htm",
          "media_type": "text/html"
        },
        {
          "url": "http://lawfilesext.leg.wa.gov/Biennium/2025-26/Pdf/Bills/Senate%20Passed%20Legislature/5794-S.PL.pdf",
          "media_type": "application/pdf"
        }
      ],
      "date": "",
      "classification": ""
    }
  ],
  "documents": [
    {
      "note": "Amendment ABEL H2365.1",
      "links": [
        {
          "url": "http://lawfilesext.leg.wa.gov/Biennium/2025-26/Htm/Amendments/House/5794-S.E%20AMH%20ABEL%20H2365.1.htm",
          "media_type": "text/html"
        }
      ],
      "date": "",
      "classification": ""
    },
    {
      "note": "Amendment BER KRNG 116",
      "links": [
        {
          "url": "http://lawfilesext.leg.wa.gov/Biennium/2025-26/Htm/Amendments/House/5794-S.E%20AMH%20BER%20KRNG%20116.htm",
          "media_type": "text/html"
        }
      ],
      "date": "",
      "classification": ""
    },
    {
      "note": "Amendment CALD KRNG 114",
      "links": [
        {
          "url": "http://lawfilesext.leg.wa.gov/Biennium/2025-26/Htm/Amendments/House/5794-S.E%20AMH%20CALD%20KRNG%20114.htm",
          "media_type": "text/html"
        }
      ],
      "date": "",
      "classification": ""
    },
    {
      "note": "Amendment CHAS H2363.1",
      "links": [
        {
          "url": "http://lawfilesext.leg.wa.gov/Biennium/2025-26/Htm/Amendments/House/5794-S.E%20AMH%20CHAS%20H2363.1.htm",
          "media_type": "text/html"
        }
      ],
      "date": "",
      "classification": ""
    },
    {
      "note": "Amendment ENGR H2325.E",
      "links": [
        {
          "url": "http://lawfilesext.leg.wa.gov/Biennium/2025-26/Htm/Amendments/House/5794-S.E%20AMH%20ENGR%20H2325.E.htm",
          "media_type": "text/html"
        }
      ],
      "date": "",
      "classification": ""
    },
    {
      "note": "Amendment FIN H2325.1",
      "links": [
        {
          "url": "http://lawfilesext.leg.wa.gov/Biennium/2025-26/Htm/Amendments/House/5794-S.E%20AMH%20FIN%20H2325.1.htm",
          "media_type": "text/html"
        }
      ],
      "date": "",
      "classification": ""
    },
    {
      "note": "Amendment GRIF KRNG 115",
      "links": [
        {
          "url": "http://lawfilesext.leg.wa.gov/Biennium/2025-26/Htm/Amendments/House/5794-S.E%20AMH%20GRIF%20KRNG%20115.htm",
          "media_type": "text/html"
        }
      ],
      "date": "",
      "classification": ""
    },
    {
      "note": "Amendment JACO H2364.1",
      "links": [
        {
          "url": "http://lawfilesext.leg.wa.gov/Biennium/2025-26/Htm/Amendments/House/5794-S.E%20AMH%20JACO%20H2364.1.htm",
          "media_type": "text/html"
        }
      ],
      "date": "",
      "classification": ""
    },
    {
      "note": "Amendment ORCU H2362.1",
      "links": [
        {
          "url": "http://lawfilesext.leg.wa.gov/Biennium/2025-26/Htm/Amendments/House/5794-S.E%20AMH%20ORCU%20H2362.1.htm",
          "media_type": "text/html"
        }
      ],
      "date": "",
      "classification": ""
    },
    {
      "note": "Amendment ORCU H2366.1",
      "links": [
        {
          "url": "http://lawfilesext.leg.wa.gov/Biennium/2025-26/Htm/Amendments/House/5794-S.E%20AMH%20ORCU%20H2366.1.htm",
          "media_type": "text/html"
        }
      ],
      "date": "",
      "classification": ""
    },
    {
      "note": "Report for Engrossed Substitute",
      "links": [
        {
          "url": "http://lawfilesext.leg.wa.gov/Biennium/2025-26/Htm/Bill%20Reports/House/5794-S.E%20HBA%20FIN%2025.htm",
          "media_type": "text/html"
        },
        {
          "url": "http://lawfilesext.leg.wa.gov/Biennium/2025-26/Htm/Bill%20Reports/House/5794-S.E%20HBR%20APH%2025.htm",
          "media_type": "text/html"
        },
        {
          "url": "http://lawfilesext.leg.wa.gov/Biennium/2025-26/Htm/Bill%20Reports/House/5794-S.E%20HBR%20FIN%2025.htm",
          "media_type": "text/html"
        }
      ],
      "date": "",
      "classification": ""
    }
  ],
  "citations": [
    {
      "publication": "Revised Code of Washington",
      "citation": "36.100.090",
      "citation_type": "final",
      "effective": null,
      "expires": null,
      "url": "https://app.leg.wa.gov/RCW/default.aspx?cite=36.100.090"
    },
    {
      "publication": "Revised Code of Washington",
      "citation": "36.102.070",
      "citation_type": "final",
      "effective": null,
      "expires": null,
      "url": "https://app.leg.wa.gov/RCW/default.aspx?cite=36.102.070"
    },
    {
      "publication": "Revised Code of Washington",
      "citation": "48.14.0201",
      "citation_type": "final",
      "effective": null,
      "expires": null,
      "url": "https://app.leg.wa.gov/RCW/default.aspx?cite=48.14.0201"
    },
    {
      "publication": "Revised Code of Washington",
      "citation": "82.04.050",
      "citation_type": "final",
      "effective": null,
      "expires": null,
      "url": "https://app.leg.wa.gov/RCW/default.aspx?cite=82.04.050"
    },
    {
      "publication": "Revised Code of Washington",
      "citation": "82.04.051",
      "citation_type": "final",
      "effective": null,
      "expires": null,
      "url": "https://app.leg.wa.gov/RCW/default.aspx?cite=82.04.051"
    },
    {
      "publication": "Revised Code of Washington",
      "citation": "82.04.062",
      "citation_type": "final",
      "effective": null,
      "expires": null,
      "url": "https://app.leg.wa.gov/RCW/default.aspx?cite=82.04.062"
    },
    {
      "publication": "Revised Code of Washington",
      "citation": "82.04.110",
      "citation_type": "final",
      "effective": null,
      "expires": null,
      "url": "https://app.leg.wa.gov/RCW/default.aspx?cite=82.04.110"
    },
    {
      "publication": "Revised Code of Washington",
      "citation": "82.04.120",
      "citation_type": "final",
      "effective": null,
      "expires": null,
      "url": "https://app.leg.wa.gov/RCW/default.aspx?cite=82.04.120"
    },
    {
      "publication": "Revised Code of Washington",
      "citation": "82.04.257",
      "citation_type": "final",
      "effective": null,
      "expires": null,
      "url": "https://app.leg.wa.gov/RCW/default.aspx?cite=82.04.257"
    },
    {
      "publication": "Revised Code of Washington",
      "citation": "82.04.260",
      "citation_type": "final",
      "effective": null,
      "expires": null,
      "url": "https://app.leg.wa.gov/RCW/default.aspx?cite=82.04.260"
    },
    {
      "publication": "Revised Code of Washington",
      "citation": "82.04.260",
      "citation_type": "final",
      "effective": null,
      "expires": null,
      "url": "https://app.leg.wa.gov/RCW/default.aspx?cite=82.04.260"
    },
    {
      "publication": "Revised Code of Washington",
      "citation": "82.04.272",
      "citation_type": "final",
      "effective": null,
      "expires": null,
      "url": "https://app.leg.wa.gov/RCW/default.aspx?cite=82.04.272"
    },
    {
      "publication": "Revised Code of Washington",
      "citation": "82.04.280",
      "citation_type": "final",
      "effective": null,
      "expires": null,
      "url": "https://app.leg.wa.gov/RCW/default.aspx?cite=82.04.280"
    },
    {
      "publication": "Revised Code of Washington",
      "citation": "82.04.290",
      "citation_type": "final",
      "effective": null,
      "expires": null,
      "url": "https://app.leg.wa.gov/RCW/default.aspx?cite=82.04.290"
    },
    {
      "publication": "Revised Code of Washington",
      "citation": "82.04.29001",
      "citation_type": "final",
      "effective": null,
      "expires": null,
      "url": "https://app.leg.wa.gov/RCW/default.aspx?cite=82.04.29001"
    },
    {
      "publication": "Revised Code of Washington",
      "citation": "82.04.29002",
      "citation_type": "final",
      "effective": null,
      "expires": null,
      "url": "https://app.leg.wa.gov/RCW/default.aspx?cite=82.04.29002"
    },
    {
      "publication": "Revised Code of Washington",
      "citation": "82.04.29004",
      "citation_type": "final",
      "effective": null,
      "expires": null,
      "url": "https://app.leg.wa.gov/RCW/default.aspx?cite=82.04.29004"
    },
    {
      "publication": "Revised Code of Washington",
      "citation": "82.04.29005",
      "citation_type": "final",
      "effective": null,
      "expires": null,
      "url": "https://app.leg.wa.gov/RCW/default.aspx?cite=82.04.29005"
    },
    {
      "publication": "Revised Code of Washington",
      "citation": "82.04.293",
      "citation_type": "final",
      "effective": null,
      "expires": null,
      "url": "https://app.leg.wa.gov/RCW/default.aspx?cite=82.04.293"
    },
    {
      "publication": "Revised Code of Washington",
      "citation": "82.04.297",
      "citation_type": "final",
      "effective": null,
      "expires": null,
      "url": "https://app.leg.wa.gov/RCW/default.aspx?cite=82.04.297"
    },
    {
      "publication": "Revised Code of Washington",
      "citation": "82.04.299",
      "citation_type": "final",
      "effective": null,
      "expires": null,
      "url": "https://app.leg.wa.gov/RCW/default.aspx?cite=82.04.299"
    },
    {
      "publication": "Revised Code of Washington",
      "citation": "82.04.315",
      "citation_type": "final",
      "effective": null,
      "expires": null,
      "url": "https://app.leg.wa.gov/RCW/default.aspx?cite=82.04.315"
    },
    {
      "publication": "Revised Code of Washington",
      "citation": "82.04.360",
      "citation_type": "final",
      "effective": null,
      "expires": null,
      "url": "https://app.leg.wa.gov/RCW/default.aspx?cite=82.04.360"
    },
    {
      "publication": "Revised Code of Washington",
      "citation": "82.04.421",
      "citation_type": "final",
      "effective": null,
      "expires": null,
      "url": "https://app.leg.wa.gov/RCW/default.aspx?cite=82.04.421"
    },
    {
      "publication": "Revised Code of Washington",
      "citation": "82.04.4292",
      "citation_type": "final",
      "effective": null,
      "expires": null,
      "url": "https://app.leg.wa.gov/RCW/default.aspx?cite=82.04.4292"
    },
    {
      "publication": "Revised Code of Washington",
      "citation": "82.04.4295",
      "citation_type": "final",
      "effective": null,
      "expires": null,
      "url": "https://app.leg.wa.gov/RCW/default.aspx?cite=82.04.4295"
    },
    {
      "publication": "Revised Code of Washington",
      "citation": "82.04.4331",
      "citation_type": "final",
      "effective": null,
      "expires": null,
      "url": "https://app.leg.wa.gov/RCW/default.aspx?cite=82.04.4331"
    },
    {
      "publication": "Revised Code of Washington",
      "citation": "82.04.4332",
      "citation_type": "final",
      "effective": null,
      "expires": null,
      "url": "https://app.leg.wa.gov/RCW/default.aspx?cite=82.04.4332"
    },
    {
      "publication": "Revised Code of Washington",
      "citation": "82.04.43391",
      "citation_type": "final",
      "effective": null,
      "expires": null,
      "url": "https://app.leg.wa.gov/RCW/default.aspx?cite=82.04.43391"
    },
    {
      "publication": "Revised Code of Washington",
      "citation": "82.04.43395",
      "citation_type": "final",
      "effective": null,
      "expires": null,
      "url": "https://app.leg.wa.gov/RCW/default.aspx?cite=82.04.43395"
    },
    {
      "publication": "Revised Code of Washington",
      "citation": "82.04.43396",
      "citation_type": "final",
      "effective": null,
      "expires": null,
      "url": "https://app.leg.wa.gov/RCW/default.aspx?cite=82.04.43396"
    },
    {
      "publication": "Revised Code of Washington",
      "citation": "82.04.434",
      "citation_type": "final",
      "effective": null,
      "expires": null,
      "url": "https://app.leg.wa.gov/RCW/default.aspx?cite=82.04.434"
    },
    {
      "publication": "Revised Code of Washington",
      "citation": "82.04.4451",
      "citation_type": "final",
      "effective": null,
      "expires": null,
      "url": "https://app.leg.wa.gov/RCW/default.aspx?cite=82.04.4451"
    },
    {
      "publication": "Revised Code of Washington",
      "citation": "82.04.44525",
      "citation_type": "final",
      "effective": null,
      "expires": null,
      "url": "https://app.leg.wa.gov/RCW/default.aspx?cite=82.04.44525"
    },
    {
      "publication": "Revised Code of Washington",
      "citation": "82.04.447",
      "citation_type": "final",
      "effective": null,
      "expires": null,
      "url": "https://app.leg.wa.gov/RCW/default.aspx?cite=82.04.447"
    },
    {
      "publication": "Revised Code of Washington",
      "citation": "82.04.4482",
      "citation_type": "final",
      "effective": null,
      "expires": null,
      "url": "https://app.leg.wa.gov/RCW/default.aspx?cite=82.04.4482"
    },
    {
      "publication": "Revised Code of Washington",
      "citation": "82.04.4496",
      "citation_type": "final",
      "effective": null,
      "expires": null,
      "url": "https://app.leg.wa.gov/RCW/default.aspx?cite=82.04.4496"
    },
    {
      "publication": "Revised Code of Washington",
      "citation": "82.04.540",
      "citation_type": "final",
      "effective": null,
      "expires": null,
      "url": "https://app.leg.wa.gov/RCW/default.aspx?cite=82.04.540"
    },
    {
      "publication": "Revised Code of Washington",
      "citation": "82.04.545",
      "citation_type": "final",
      "effective": null,
      "expires": null,
      "url": "https://app.leg.wa.gov/RCW/default.aspx?cite=82.04.545"
    },
    {
      "publication": "Revised Code of Washington",
      "citation": "82.04.620",
      "citation_type": "final",
      "effective": null,
      "expires": null,
      "url": "https://app.leg.wa.gov/RCW/default.aspx?cite=82.04.620"
    },
    {
      "publication": "Revised Code of Washington",
      "citation": "82.04.627",
      "citation_type": "final",
      "effective": null,
      "expires": null,
      "url": "https://app.leg.wa.gov/RCW/default.aspx?cite=82.04.627"
    },
    {
      "publication": "Revised Code of Washington",
      "citation": "82.08.02566",
      "citation_type": "final",
      "effective": null,
      "expires": null,
      "url": "https://app.leg.wa.gov/RCW/default.aspx?cite=82.08.02566"
    },
    {
      "publication": "Revised Code of Washington",
      "citation": "82.08.02568",
      "citation_type": "final",
      "effective": null,
      "expires": null,
      "url": "https://app.leg.wa.gov/RCW/default.aspx?cite=82.08.02568"
    },
    {
      "publication": "Revised Code of Washington",
      "citation": "82.08.02569",
      "citation_type": "final",
      "effective": null,
      "expires": null,
      "url": "https://app.leg.wa.gov/RCW/default.aspx?cite=82.08.02569"
    },
    {
      "publication": "Revised Code of Washington",
      "citation": "82.08.0262",
      "citation_type": "final",
      "effective": null,
      "expires": null,
      "url": "https://app.leg.wa.gov/RCW/default.aspx?cite=82.08.0262"
    },
    {
      "publication": "Revised Code of Washington",
      "citation": "82.08.809",
      "citation_type": "final",
      "effective": null,
      "expires": null,
      "url": "https://app.leg.wa.gov/RCW/default.aspx?cite=82.08.809"
    },
    {
      "publication": "Revised Code of Washington",
      "citation": "82.08.9999",
      "citation_type": "final",
      "effective": null,
      "expires": null,
      "url": "https://app.leg.wa.gov/RCW/default.aspx?cite=82.08.9999"
    },
    {
      "publication": "Revised Code of Washington",
      "citation": "82.12.022",
      "citation_type": "final",
      "effective": null,
      "expires": null,
      "url": "https://app.leg.wa.gov/RCW/default.aspx?cite=82.12.022"
    },
    {
      "publication": "Revised Code of Washington",
      "citation": "82.12.024",
      "citation_type": "final",
      "effective": null,
      "expires": null,
      "url": "https://app.leg.wa.gov/RCW/default.aspx?cite=82.12.024"
    },
    {
      "publication": "Revised Code of Washington",
      "citation": "82.12.0254",
      "citation_type": "final",
      "effective": null,
      "expires": null,
      "url": "https://app.leg.wa.gov/RCW/default.aspx?cite=82.12.0254"
    },
    {
      "publication": "Revised Code of Washington",
      "citation": "82.12.02566",
      "citation_type": "final",
      "effective": null,
      "expires": null,
      "url": "https://app.leg.wa.gov/RCW/default.aspx?cite=82.12.02566"
    },
    {
      "publication": "Revised Code of Washington",
      "citation": "82.12.02568",
      "citation_type": "final",
      "effective": null,
      "expires": null,
      "url": "https://app.leg.wa.gov/RCW/default.aspx?cite=82.12.02568"
    },
    {
      "publication": "Revised Code of Washington",
      "citation": "82.12.02569",
      "citation_type": "final",
      "effective": null,
      "expires": null,
      "url": "https://app.leg.wa.gov/RCW/default.aspx?cite=82.12.02569"
    },
    {
      "publication": "Revised Code of Washington",
      "citation": "82.12.0265",
      "citation_type": "final",
      "effective": null,
      "expires": null,
      "url": "https://app.leg.wa.gov/RCW/default.aspx?cite=82.12.0265"
    },
    {
      "publication": "Revised Code of Washington",
      "citation": "82.12.809",
      "citation_type": "final",
      "effective": null,
      "expires": null,
      "url": "https://app.leg.wa.gov/RCW/default.aspx?cite=82.12.809"
    },
    {
      "publication": "Revised Code of Washington",
      "citation": "82.12.9999",
      "citation_type": "final",
      "effective": null,
      "expires": null,
      "url": "https://app.leg.wa.gov/RCW/default.aspx?cite=82.12.9999"
    },
    {
      "publication": "Revised Code of Washington",
      "citation": "82.16.020",
      "citation_type": "final",
      "effective": null,
      "expires": null,
      "url": "https://app.leg.wa.gov/RCW/default.aspx?cite=82.16.020"
    },
    {
      "publication": "Revised Code of Washington",
      "citation": "82.16.046",
      "citation_type": "final",
      "effective": null,
      "expires": null,
      "url": "https://app.leg.wa.gov/RCW/default.aspx?cite=82.16.046"
    },
    {
      "publication": "Revised Code of Washington",
      "citation": "82.16.0495",
      "citation_type": "final",
      "effective": null,
      "expires": null,
      "url": "https://app.leg.wa.gov/RCW/default.aspx?cite=82.16.0495"
    },
    {
      "publication": "Revised Code of Washington",
      "citation": "82.16.0496",
      "citation_type": "final",
      "effective": null,
      "expires": null,
      "url": "https://app.leg.wa.gov/RCW/default.aspx?cite=82.16.0496"
    },
    {
      "publication": "Revised Code of Washington",
      "citation": "82.16.0497",
      "citation_type": "final",
      "effective": null,
      "expires": null,
      "url": "https://app.leg.wa.gov/RCW/default.aspx?cite=82.16.0497"
    },
    {
      "publication": "Revised Code of Washington",
      "citation": "82.16.0498",
      "citation_type": "final",
      "effective": null,
      "expires": null,
      "url": "https://app.leg.wa.gov/RCW/default.aspx?cite=82.16.0498"
    },
    {
      "publication": "Revised Code of Washington",
      "citation": "82.16.050",
      "citation_type": "final",
      "effective": null,
      "expires": null,
      "url": "https://app.leg.wa.gov/RCW/default.aspx?cite=82.16.050"
    },
    {
      "publication": "Revised Code of Washington",
      "citation": "82.16.315",
      "citation_type": "final",
      "effective": null,
      "expires": null,
      "url": "https://app.leg.wa.gov/RCW/default.aspx?cite=82.16.315"
    },
    {
      "publication": "Revised Code of Washington",
      "citation": "82.21.040",
      "citation_type": "final",
      "effective": null,
      "expires": null,
      "url": "https://app.leg.wa.gov/RCW/default.aspx?cite=82.21.040"
    },
    {
      "publication": "Revised Code of Washington",
      "citation": "82.23a.030",
      "citation_type": "final",
      "effective": null,
      "expires": null,
      "url": "https://app.leg.wa.gov/RCW/default.aspx?cite=82.23a.030"
    },
    {
      "publication": "Revised Code of Washington",
      "citation": "82.29a.130",
      "citation_type": "final",
      "effective": null,
      "expires": null,
      "url": "https://app.leg.wa.gov/RCW/default.aspx?cite=82.29a.130"
    },
    {
      "publication": "Revised Code of Washington",
      "citation": "82.29a.132",
      "citation_type": "final",
      "effective": null,
      "expires": null,
      "url": "https://app.leg.wa.gov/RCW/default.aspx?cite=82.29a.132"
    },
    {
      "publication": "Revised Code of Washington",
      "citation": "82.29a.137",
      "citation_type": "final",
      "effective": null,
      "expires": null,
      "url": "https://app.leg.wa.gov/RCW/default.aspx?cite=82.29a.137"
    },
    {
      "publication": "Revised Code of Washington",
      "citation": "82.32.805",
      "citation_type": "final",
      "effective": null,
      "expires": null,
      "url": "https://app.leg.wa.gov/RCW/default.aspx?cite=82.32.805"
    },
    {
      "publication": "Revised Code of Washington",
      "citation": "82.32.808",
      "citation_type": "final",
      "effective": null,
      "expires": null,
      "url": "https://app.leg.wa.gov/RCW/default.aspx?cite=82.32.808"
    },
    {
      "publication": "Revised Code of Washington",
      "citation": "82.45.010",
      "citation_type": "final",
      "effective": null,
      "expires": null,
      "url": "https://app.leg.wa.gov/RCW/default.aspx?cite=82.45.010"
    },
    {
      "publication": "Revised Code of Washington",
      "citation": "82.45.030",
      "citation_type": "final",
      "effective": null,
      "expires": null,
      "url": "https://app.leg.wa.gov/RCW/default.aspx?cite=82.45.030"
    },
    {
      "publication": "Revised Code of Washington",
      "citation": "82.45.190",
      "citation_type": "final",
      "effective": null,
      "expires": null,
      "url": "https://app.leg.wa.gov/RCW/default.aspx?cite=82.45.190"
    },
    {
      "publication": "Revised Code of Washington",
      "citation": "82.48.030",
      "citation_type": "final",
      "effective": null,
      "expires": null,
      "url": "https://app.leg.wa.gov/RCW/default.aspx?cite=82.48.030"
    },
    {
      "publication": "Revised Code of Washington",
      "citation": "82.62.030",
      "citation_type": "final",
      "effective": null,
      "expires": null,
      "url": "https://app.leg.wa.gov/RCW/default.aspx?cite=82.62.030"
    },
    {
      "publication": "Revised Code of Washington",
      "citation": "82.64.030",
      "citation_type": "final",
      "effective": null,
      "expires": null,
      "url": "https://app.leg.wa.gov/RCW/default.aspx?cite=82.64.030"
    },
    {
      "publication": "Revised Code of Washington",
      "citation": "82.85.010",
      "citation_type": "final",
      "effective": null,
      "expires": null,
      "url": "https://app.leg.wa.gov/RCW/default.aspx?cite=82.85.010"
    },
    {
      "publication": "Revised Code of Washington",
      "citation": "82.85.020",
      "citation_type": "final",
      "effective": null,
      "expires": null,
      "url": "https://app.leg.wa.gov/RCW/default.aspx?cite=82.85.020"
    },
    {
      "publication": "Revised Code of Washington",
      "citation": "82.85.040",
      "citation_type": "final",
      "effective": null,
      "expires": null,
      "url": "https://app.leg.wa.gov/RCW/default.aspx?cite=82.85.040"
    },
    {
      "publication": "Revised Code of Washington",
      "citation": "84.36.010",
      "citation_type": "final",
      "effective": null,
      "expires": null,
      "url": "https://app.leg.wa.gov/RCW/default.aspx?cite=84.36.010"
    },
    {
      "publication": "Revised Code of Washington",
      "citation": "84.36.030",
      "citation_type": "final",
      "effective": null,
      "expires": null,
      "url": "https://app.leg.wa.gov/RCW/default.aspx?cite=84.36.030"
    }
  ],
  "sources": [
    {
      "url": "https://app.leg.wa.gov/billsummary/?BillNumber=5794&Year=2025&Initiative=false",
      "note": ""
    }
  ],
  "extras": {},
  "jurisdiction": {
    "id": "ocd-jurisdiction/country:us/state:wa/government",
    "name": "Washington",
    "classification": "state",
    "division_id": "ocd-division/country:us/state:wa"
  },
  "_processing": {
    "logs_latest_update": "2025-10-25T03:55:00Z",
    "text_extraction_latest_update": "2025-10-30T09:06:50.333462Z"
  }
}