{
  "legislative_session": "2025-2026",
  "identifier": "SB 5734",
  "title": "Concerning the interstate bridge replacement toll bond authority.",
  "from_organization": "~{\"classification\": \"upper\"}",
  "classification": [
    "bill"
  ],
  "subject": [],
  "abstracts": [],
  "other_titles": [],
  "other_identifiers": [],
  "actions": [
    {
      "description": "First reading, referred to Transportation.",
      "date": "2025-02-12",
      "organization_id": "~{\"classification\": \"upper\"}",
      "classification": [
        "reading-1"
      ],
      "related_entities": [],
      "_processing": {
        "log_file_created": "2025-10-25T03:55:01Z"
      }
    },
    {
      "description": "Public hearing in the Senate Committee on Transportation at 1:30 PM.",
      "date": "2025-02-25",
      "organization_id": "~{\"classification\": \"upper\"}",
      "classification": [],
      "related_entities": [],
      "_processing": {
        "log_file_created": "2025-10-25T03:55:01Z"
      }
    },
    {
      "description": "Executive action taken in the Senate Committee on Transportation at 1:30 PM.",
      "date": "2025-04-08",
      "organization_id": "~{\"classification\": \"upper\"}",
      "classification": [],
      "related_entities": [],
      "_processing": {
        "log_file_created": "2025-10-25T03:55:01Z"
      }
    },
    {
      "description": "TRAN - Majority; 1st substitute bill be substituted, do pass.",
      "date": "2025-04-08",
      "organization_id": "~{\"classification\": \"upper\"}",
      "classification": [
        "substitution"
      ],
      "related_entities": [],
      "_processing": {
        "log_file_created": "2025-10-25T03:55:01Z"
      }
    },
    {
      "description": "Minority; do not pass.",
      "date": "2025-04-08",
      "organization_id": "~{\"classification\": \"upper\"}",
      "classification": [
        "committee-passage-unfavorable"
      ],
      "related_entities": [],
      "_processing": {
        "log_file_created": "2025-10-25T03:55:01Z"
      }
    },
    {
      "description": "Passed to Rules Committee for second reading.",
      "date": "2025-04-08",
      "organization_id": "~{\"classification\": \"upper\"}",
      "classification": [],
      "related_entities": [],
      "_processing": {
        "log_file_created": "2025-10-25T03:55:01Z"
      }
    }
  ],
  "sponsorships": [
    {
      "name": "Liias",
      "classification": "primary",
      "entity_type": "person",
      "primary": true,
      "person_id": "~{\"name\": \"Liias\"}",
      "organization_id": null
    },
    {
      "name": "Harris",
      "classification": "cosponsor",
      "entity_type": "person",
      "primary": false,
      "person_id": "~{\"name\": \"Harris\"}",
      "organization_id": null
    },
    {
      "name": "Cleveland",
      "classification": "cosponsor",
      "entity_type": "person",
      "primary": false,
      "person_id": "~{\"name\": \"Cleveland\"}",
      "organization_id": null
    },
    {
      "name": "Cortes",
      "classification": "cosponsor",
      "entity_type": "person",
      "primary": false,
      "person_id": "~{\"name\": \"Cortes\"}",
      "organization_id": null
    },
    {
      "name": "King",
      "classification": "cosponsor",
      "entity_type": "person",
      "primary": false,
      "person_id": "~{\"name\": \"King\"}",
      "organization_id": null
    }
  ],
  "related_bills": [],
  "versions": [
    {
      "note": "Substitute Bill",
      "links": [
        {
          "url": "http://lawfilesext.leg.wa.gov/Biennium/2025-26/Htm/Bills/Senate%20Bills/5734-S.htm",
          "media_type": "text/html"
        },
        {
          "url": "http://lawfilesext.leg.wa.gov/Biennium/2025-26/Pdf/Bills/Senate%20Bills/5734-S.pdf",
          "media_type": "application/pdf"
        }
      ],
      "date": "",
      "classification": ""
    },
    {
      "note": "Bill",
      "links": [
        {
          "url": "http://lawfilesext.leg.wa.gov/Biennium/2025-26/Htm/Bills/Senate%20Bills/5734.htm",
          "media_type": "text/html"
        },
        {
          "url": "http://lawfilesext.leg.wa.gov/Biennium/2025-26/Pdf/Bills/Senate%20Bills/5734.pdf",
          "media_type": "application/pdf"
        }
      ],
      "date": "",
      "classification": ""
    }
  ],
  "documents": [],
  "citations": [
    {
      "publication": "Revised Code of Washington",
      "citation": "47.10",
      "citation_type": "proposed",
      "effective": null,
      "expires": null,
      "url": "https://app.leg.wa.gov/RCW/default.aspx?cite=47.10"
    },
    {
      "publication": "Revised Code of Washington",
      "citation": "47.10.905",
      "citation_type": "proposed",
      "effective": null,
      "expires": null,
      "url": "https://app.leg.wa.gov/RCW/default.aspx?cite=47.10.905"
    },
    {
      "publication": "Revised Code of Washington",
      "citation": "47.10.906",
      "citation_type": "proposed",
      "effective": null,
      "expires": null,
      "url": "https://app.leg.wa.gov/RCW/default.aspx?cite=47.10.906"
    },
    {
      "publication": "Revised Code of Washington",
      "citation": "47.10.907",
      "citation_type": "proposed",
      "effective": null,
      "expires": null,
      "url": "https://app.leg.wa.gov/RCW/default.aspx?cite=47.10.907"
    }
  ],
  "sources": [
    {
      "url": "https://app.leg.wa.gov/billsummary/?BillNumber=5734&Year=2025&Initiative=false",
      "note": ""
    }
  ],
  "extras": {},
  "jurisdiction": {
    "id": "ocd-jurisdiction/country:us/state:wa/government",
    "name": "Washington",
    "classification": "state",
    "division_id": "ocd-division/country:us/state:wa"
  },
  "_processing": {
    "logs_latest_update": "2025-10-25T03:55:01Z",
    "text_extraction_latest_update": "2025-10-30T09:36:07.541368Z"
  }
}